README.md
setup.py
superpowers.py
superpowers.egg-info/PKG-INFO
superpowers.egg-info/SOURCES.txt
superpowers.egg-info/dependency_links.txt
superpowers.egg-info/not-zip-safe
superpowers.egg-info/requires.txt
superpowers.egg-info/top_level.txt