Metadata-Version: 1.1
Name: superpowers
Version: 0.1.2
Summary: Scala-like map for Python, do [1, 2, 3].map(_*3)
Home-page: UNKNOWN
Author: Teemu
Author-email: teemu.on.ihminen@gmail.com
License: BSD
Platform: any
Classifier: Programming Language :: Python :: 3
Classifier: Programming Language :: Python :: 3.4
Classifier: Programming Language :: Python :: 3.5
Classifier: Programming Language :: Python :: 3.6
